xplot/__init__.py
xplot/xplot.py
xplot-0.0.5.dist-info/METADATA
xplot-0.0.5.dist-info/WHEEL
xplot-0.0.5.dist-info/top_level.txt
xplot-0.0.5.dist-info/RECORD
